byted_overpass_iestns_china_qianxun_core/__init__.py
byted_overpass_iestns_china_qianxun_core-0.0.1.dist-info/METADATA
byted_overpass_iestns_china_qianxun_core-0.0.1.dist-info/WHEEL
byted_overpass_iestns_china_qianxun_core-0.0.1.dist-info/top_level.txt
byted_overpass_iestns_china_qianxun_core-0.0.1.dist-info/RECORD
